odoo9_addon_document_page_health_safety_manual-9.0.1.0.0.99.dev2-py2.7-nspkg.pth
odoo9_addon_document_page_health_safety_manual-9.0.1.0.0.99.dev2.dist-info/DESCRIPTION.rst
odoo9_addon_document_page_health_safety_manual-9.0.1.0.0.99.dev2.dist-info/METADATA
odoo9_addon_document_page_health_safety_manual-9.0.1.0.0.99.dev2.dist-info/RECORD
odoo9_addon_document_page_health_safety_manual-9.0.1.0.0.99.dev2.dist-info/WHEEL
odoo9_addon_document_page_health_safety_manual-9.0.1.0.0.99.dev2.dist-info/metadata.json
odoo9_addon_document_page_health_safety_manual-9.0.1.0.0.99.dev2.dist-info/namespace_packages.txt
odoo9_addon_document_page_health_safety_manual-9.0.1.0.0.99.dev2.dist-info/top_level.txt
odoo_addons/document_page_health_safety_manual/README.rst
odoo_addons/document_page_health_safety_manual/__init__.py
odoo_addons/document_page_health_safety_manual/__openerp__.py
odoo_addons/document_page_health_safety_manual/data/document_page.xml
odoo_addons/document_page_health_safety_manual/i18n/document_page_health_safety_manual.pot
odoo_addons/document_page_health_safety_manual/migrations/7.0.1.0/post-migration.py
odoo_addons/document_page_health_safety_manual/static/description/icon.png
